if_stage.sv
// will contain PC Logic, Instruction Memory reading


module if_stage #(parameter WIDTH)
                (input clk, rst,
                input PCSrc,
                input [WIDTH-1:0] pc_br,
                output reg [WIDTH-1:0] pc_pp,
                output wire [WIDTH-1:0] inst_mem_out);

    // program counter
    reg [WIDTH-1:0] pc;

    // need Instruction Memory
    reg [WIDTH-1:0] instruction_memory [32-1:0]; // for 32 instructions, can adjust
    integer i = 0;
    initial begin
        for(i = 0; i < 31; i++) begin
            instruction_memory[i] = i;
        end
    end

    always_ff @(posedge clk or posedge rst) begin
        // condition ? value_if_true : value_if_false
        if(rst)   pc <= '0;
        else        pc <= PCSrc ? pc_br : (pc + 4);
    end

    always_comb  begin
        // could keep this, or change to be an ALU which ONLY adds by 4
        pc_pp = (pc + 4);
        if(rst) begin
            inst_mem_out = 32'b0;
        end
        else begin 
            inst_mem_out = instruction_memory[pc];
        end
    end

endmodule: if_stage

tb_if.sv
// instruction fetch (IF) stage testbench


module tb_if();
        
    parameter WIDTH = 32;
    parameter CLK_PERIOD = 10;

    reg clk, rst, PCSrc;
    reg [WIDTH-1:0] pc_br;

    wire [WIDTH-1:0] pc_pp;
    wire [WIDTH-1:0] instruction;
    
    // <name of module> #(param. connections) <name of instance> (port conn.) 
    if_stage #(.WIDTH(WIDTH)) if_00 (.clk(clk), .rst(rst), .PCSrc(PCSrc), .pc_pp(pc_pp), .pc_br(pc_br), .inst_mem_out(instruction));
    
    always #(CLK_PERIOD/2) clk = ~clk;
    initial begin
        clk = 0; rst = 1; PCSrc = 0; pc_br = '0;
        #(1*CLK_PERIOD) rst = 0; // initial reset sequence
        #(6*CLK_PERIOD) PCSrc = 1; pc_br = 32'd5;
        #(1*CLK_PERIOD) PCSrc = 0;
        #(3*CLK_PERIOD) pc_br = '0;
        #(2*CLK_PERIOD) $finish;
    end

    initial begin
        $dumpfile("tb_if.vcd");
        $dumpvars(1, tb_if);
        $monitor("%t: clk %1b, rst %1b, PCSrc %1b, pc_br %5b, pc_pp %5b, instruction %32b", $time, clk, rst, PCSrc, pc_br, pc_pp, instruction);
    end



endmodule: tb_if

tb_if.vcd
$version Generated by VerilatedVcd $end
$timescale 1ps $end
 $scope module tb_if $end
  $var wire 32 J WIDTH [31:0] $end
  $var wire 32 K CLK_PERIOD [31:0] $end
  $var wire 1 C clk $end
  $var wire 1 D rst $end
  $var wire 1 E PCSrc $end
  $var wire 32 F pc_br [31:0] $end
  $var wire 32 G pc_pp [31:0] $end
  $var wire 32 H instruction [31:0] $end
  $scope module if_00 $end
   $var wire 32 J WIDTH [31:0] $end
   $var wire 1 C clk $end
   $var wire 1 D rst $end
   $var wire 1 E PCSrc $end
   $var wire 32 F pc_br [31:0] $end
   $var wire 32 G pc_pp [31:0] $end
   $var wire 32 H inst_mem_out [31:0] $end
   $var wire 32 I pc [31:0] $end
   $var wire 32 " instruction_memory[0] [31:0] $end
   $var wire 32 # instruction_memory[1] [31:0] $end
   $var wire 32 $ instruction_memory[2] [31:0] $end
   $var wire 32 % instruction_memory[3] [31:0] $end
   $var wire 32 & instruction_memory[4] [31:0] $end
   $var wire 32 ' instruction_memory[5] [31:0] $end
   $var wire 32 ( instruction_memory[6] [31:0] $end
   $var wire 32 ) instruction_memory[7] [31:0] $end
   $var wire 32 * instruction_memory[8] [31:0] $end
   $var wire 32 + instruction_memory[9] [31:0] $end
   $var wire 32 , instruction_memory[10] [31:0] $end
   $var wire 32 - instruction_memory[11] [31:0] $end
   $var wire 32 . instruction_memory[12] [31:0] $end
   $var wire 32 / instruction_memory[13] [31:0] $end
   $var wire 32 0 instruction_memory[14] [31:0] $end
   $var wire 32 1 instruction_memory[15] [31:0] $end
   $var wire 32 2 instruction_memory[16] [31:0] $end
   $var wire 32 3 instruction_memory[17] [31:0] $end
   $var wire 32 4 instruction_memory[18] [31:0] $end
   $var wire 32 5 instruction_memory[19] [31:0] $end
   $var wire 32 6 instruction_memory[20] [31:0] $end
   $var wire 32 7 instruction_memory[21] [31:0] $end
   $var wire 32 8 instruction_memory[22] [31:0] $end
   $var wire 32 9 instruction_memory[23] [31:0] $end
   $var wire 32 : instruction_memory[24] [31:0] $end
   $var wire 32 ; instruction_memory[25] [31:0] $end
   $var wire 32 < instruction_memory[26] [31:0] $end
   $var wire 32 = instruction_memory[27] [31:0] $end
   $var wire 32 > instruction_memory[28] [31:0] $end
   $var wire 32 ? instruction_memory[29] [31:0] $end
   $var wire 32 @ instruction_memory[30] [31:0] $end
   $var wire 32 A instruction_memory[31] [31:0] $end
   $var wire 32 B i [31:0] $end
  $upscope $end
 $upscope $end
$enddefinitions $end


#0
b00000000000000000000000000000000 "
b00000000000000000000000000000001 #
b00000000000000000000000000000010 $
b00000000000000000000000000000011 %
b00000000000000000000000000000100 &
b00000000000000000000000000000101 '
b00000000000000000000000000000110 (
b00000000000000000000000000000111 )
b00000000000000000000000000001000 *
b00000000000000000000000000001001 +
b00000000000000000000000000001010 ,
b00000000000000000000000000001011 -
b00000000000000000000000000001100 .
b00000000000000000000000000001101 /
b00000000000000000000000000001110 0
b00000000000000000000000000001111 1
b00000000000000000000000000010000 2
b00000000000000000000000000010001 3
b00000000000000000000000000010010 4
b00000000000000000000000000010011 5
b00000000000000000000000000010100 6
b00000000000000000000000000010101 7
b00000000000000000000000000010110 8
b00000000000000000000000000010111 9
b00000000000000000000000000011000 :
b00000000000000000000000000011001 ;
b00000000000000000000000000011010 <
b00000000000000000000000000011011 =
b00000000000000000000000000011100 >
b00000000000000000000000000011101 ?
b00000000000000000000000000011110 @
b00000000000000000000000000000000 A
b00000000000000000000000000011111 B
0C
1D
0E
b00000000000000000000000000000000 F
b00000000000000000000000000000100 G
b00000000000000000000000000000000 H
b00000000000000000000000000000000 I
b00000000000000000000000000100000 J
b00000000000000000000000000001010 K
#5
1C
#10
0C
0D
#15
1C
b00000000000000000000000000001000 G
b00000000000000000000000000000100 H
b00000000000000000000000000000100 I
#20
0C
#25
1C
b00000000000000000000000000001100 G
b00000000000000000000000000001000 H
b00000000000000000000000000001000 I
#30
0C
#35
1C
b00000000000000000000000000010000 G
b00000000000000000000000000001100 H
b00000000000000000000000000001100 I
#40
0C
#45
1C
b00000000000000000000000000010100 G
b00000000000000000000000000010000 H
b00000000000000000000000000010000 I
#50
0C
#55
1C
b00000000000000000000000000011000 G
b00000000000000000000000000010100 H
b00000000000000000000000000010100 I
#60
0C
#65
1C
b00000000000000000000000000011100 G
b00000000000000000000000000011000 H
b00000000000000000000000000011000 I
#70
0C
1E
b00000000000000000000000000000101 F
#75
1C
b00000000000000000000000000001001 G
b00000000000000000000000000000101 H
b00000000000000000000000000000101 I
#80
0C
0E
#85
1C
b00000000000000000000000000001101 G
b00000000000000000000000000001001 H
b00000000000000000000000000001001 I
#90
0C
#95
1C
b00000000000000000000000000010001 G
b00000000000000000000000000001101 H
b00000000000000000000000000001101 I
#100
0C
#105
1C
b00000000000000000000000000010101 G
b00000000000000000000000000010001 H
b00000000000000000000000000010001 I
#110
0C
b00000000000000000000000000000000 F
#115
1C
b00000000000000000000000000011001 G
b00000000000000000000000000010101 H
b00000000000000000000000000010101 I
#120
0C
#125
1C
b00000000000000000000000000011101 G
b00000000000000000000000000011001 H
b00000000000000000000000000011001 I
