mem_stage.sv
`timescale 1ns/1ns
// Data Memory Read/Write
module mem_stage #(parameter WIDTH) (
    input clk, rst,
    input logic zero_flag,
    input reg [2:0] mem_ctrl,
    input reg [1:0] wb_ctrl_in,
    input reg [WIDTH-1:0] alu_result, rd_data_two_out, pc_slt_add,
    input reg [4:0] reg_dst_mux,

    output wire branch_flag,
    output logic [WIDTH-1:0] mem_read_data, branch_addr, alu_result_out,
    output logic [1:0] wb_ctrl_out,
    output wire [4:0] wr_reg_dest_out
    );

    assign wb_ctrl_out = wb_ctrl_in;

    assign branch_flag = mem_ctrl[2] & zero_flag;

    assign wr_reg_dest_out = reg_dst_mux;

    assign branch_addr = pc_slt_add;
    assign alu_result_out = alu_result;

    // need Data Memory
    reg [WIDTH-1:0] data_memory [32-1:0]; // for 32 memory entries, can adjust of course
    integer i = 0;
    initial begin
        for(i = 0; i < 32; i++) begin
            data_memory[i] = i;
        end
    end

/* "mem_ctrl" is 3 bits:
    [0] - MemRead
    [1] - MemWrite
    [2] - Branch
*/

    // combinational read
    assign mem_read_data = mem_ctrl[1] ? data_memory[alu_result] : '0;

    // clocked write
    always_ff @(posedge clk) begin
        if(mem_ctrl[0] & ~rst)
            data_memory[alu_result] <= rd_data_two_out;
    end

endmodule: mem_stage

tb_mem.sv
`timescale 1ns/1ns
// Memory Access (MEM) Stage
module tb_mem();
// parameters
    parameter WIDTH = 32;
    parameter CLK_PERIOD = 10;

// input regs declaration
    reg [2:0] mem_ctrl;
    reg [1:0] wb_ctrl_in;
    reg [WIDTH-1:0] pc_slt_add, alu_result, rd_data_two_out;
    reg zero_flag;
    reg [4:0] reg_dst_mux;

// output wire declaration
    wire branch_flag;
    wire [1:0] wb_ctrl_out;
    wire [WIDTH-1:0] mem_read_data, branch_addr, alu_result_out;
    wire [4:0] wr_reg_dest_out;

// initialize clk, period 10ns
    reg clk, rst;
    always #(CLK_PERIOD/2) clk = ~clk;

// module instantiation
    mem_stage # (.WIDTH(WIDTH)) mem_00 (.mem_ctrl(mem_ctrl),
        .rst(rst),
        .clk(clk),
        .wb_ctrl_in(wb_ctrl_in),
        .pc_slt_add(pc_slt_add),
        .alu_result(alu_result),
        .rd_data_two_out(rd_data_two_out),
        .zero_flag(zero_flag),
        .reg_dst_mux(reg_dst_mux),
        .branch_flag(branch_flag),
        .wb_ctrl_out(wb_ctrl_out),
        .mem_read_data(mem_read_data),
        .branch_addr(branch_addr),
        .alu_result_out(alu_result_out),
        .wr_reg_dest_out(wr_reg_dest_out)
);

// module stimulus
    initial begin
        clk = 0; rst = 1; mem_ctrl = '0; wb_ctrl_in = '0; pc_slt_add = '0; alu_result = '0; rd_data_two_out = '0; zero_flag = '0; reg_dst_mux = '0;
        #(CLK_PERIOD) rst = 0;

    // test branch flag functionality
        #(CLK_PERIOD) mem_ctrl[2] = 1;
        #(CLK_PERIOD) mem_ctrl[2] = 0; zero_flag = 1;
        #(CLK_PERIOD) mem_ctrl[2] = 1; zero_flag = 0;


    // test data memory
            // read value from address a in data memory
        #(CLK_PERIOD) alu_result = 6; mem_ctrl[2] = 0; mem_ctrl[1] = 1; 
            // write to address a
        #(CLK_PERIOD) alu_result = 6; mem_ctrl[1] = 0; mem_ctrl[0] = 1; rd_data_two_out = 67;
            // read again from address a
        #(CLK_PERIOD) alu_result = 6; mem_ctrl[1] = 1; mem_ctrl[0] = 0;

        #(2*CLK_PERIOD) $finish;
    end


// waveform instantiation
    initial begin
        $dumpfile("tb_mem.vcd");
        $dumpvars(1, tb_mem);
        $monitor("%t: clk %1b, rst %1b, mem_ctrl %3b, wb_ctrl_in %2b, pc_slt_add %32b, alu_result %32b, rd_data_two_out %32b, wb_ctrl_out %2b, branch_flag %1b, mem_read_data %32b, branch_addr %32b, alu_result_out %32b, wr_reg_dest_out %5b",
          $time, clk, rst, mem_ctrl, wb_ctrl_in, pc_slt_add, alu_result, rd_data_two_out, wb_ctrl_out, branch_flag, mem_read_data, branch_addr, alu_result_out, wr_reg_dest_out);
    end



endmodule: tb_mem

vcd/tb_mem.vcd
$version Generated by VerilatedVcd $end
$timescale 1ns $end
 $scope module tb_mem $end
  $var wire 32 N WIDTH [31:0] $end
  $var wire 32 O CLK_PERIOD [31:0] $end
  $var wire 3 " mem_ctrl [2:0] $end
  $var wire 2 # wb_ctrl_in [1:0] $end
  $var wire 32 $ pc_slt_add [31:0] $end
  $var wire 32 % alu_result [31:0] $end
  $var wire 32 & rd_data_two_out [31:0] $end
  $var wire 1 ' zero_flag $end
  $var wire 5 ( reg_dst_mux [4:0] $end
  $var wire 1 ) branch_flag $end
  $var wire 2 # wb_ctrl_out [1:0] $end
  $var wire 32 K mem_read_data [31:0] $end
  $var wire 32 $ branch_addr [31:0] $end
  $var wire 32 % alu_result_out [31:0] $end
  $var wire 5 ( wr_reg_dest_out [4:0] $end
  $var wire 1 L clk $end
  $var wire 1 * rst $end
  $scope module mem_00 $end
   $var wire 32 N WIDTH [31:0] $end
   $var wire 1 L clk $end
   $var wire 1 * rst $end
   $var wire 1 ' zero_flag $end
   $var wire 3 " mem_ctrl [2:0] $end
   $var wire 2 # wb_ctrl_in [1:0] $end
   $var wire 32 % alu_result [31:0] $end
   $var wire 32 & rd_data_two_out [31:0] $end
   $var wire 32 $ pc_slt_add [31:0] $end
   $var wire 5 ( reg_dst_mux [4:0] $end
   $var wire 1 ) branch_flag $end
   $var wire 2 # wb_ctrl_out [1:0] $end
   $var wire 32 K mem_read_data [31:0] $end
   $var wire 32 $ branch_addr [31:0] $end
   $var wire 32 % alu_result_out [31:0] $end
   $var wire 5 ( wr_reg_dest_out [4:0] $end
   $var wire 32 + data_memory[0] [31:0] $end
   $var wire 32 , data_memory[1] [31:0] $end
   $var wire 32 - data_memory[2] [31:0] $end
   $var wire 32 . data_memory[3] [31:0] $end
   $var wire 32 / data_memory[4] [31:0] $end
   $var wire 32 0 data_memory[5] [31:0] $end
   $var wire 32 1 data_memory[6] [31:0] $end
   $var wire 32 2 data_memory[7] [31:0] $end
   $var wire 32 3 data_memory[8] [31:0] $end
   $var wire 32 4 data_memory[9] [31:0] $end
   $var wire 32 5 data_memory[10] [31:0] $end
   $var wire 32 6 data_memory[11] [31:0] $end
   $var wire 32 7 data_memory[12] [31:0] $end
   $var wire 32 8 data_memory[13] [31:0] $end
   $var wire 32 9 data_memory[14] [31:0] $end
   $var wire 32 : data_memory[15] [31:0] $end
   $var wire 32 ; data_memory[16] [31:0] $end
   $var wire 32 < data_memory[17] [31:0] $end
   $var wire 32 = data_memory[18] [31:0] $end
   $var wire 32 > data_memory[19] [31:0] $end
   $var wire 32 ? data_memory[20] [31:0] $end
   $var wire 32 @ data_memory[21] [31:0] $end
   $var wire 32 A data_memory[22] [31:0] $end
   $var wire 32 B data_memory[23] [31:0] $end
   $var wire 32 C data_memory[24] [31:0] $end
   $var wire 32 D data_memory[25] [31:0] $end
   $var wire 32 E data_memory[26] [31:0] $end
   $var wire 32 F data_memory[27] [31:0] $end
   $var wire 32 G data_memory[28] [31:0] $end
   $var wire 32 H data_memory[29] [31:0] $end
   $var wire 32 I data_memory[30] [31:0] $end
   $var wire 32 J data_memory[31] [31:0] $end
   $var wire 32 M i [31:0] $end
  $upscope $end
 $upscope $end
$enddefinitions $end


#0
b000 "
b00 #
b00000000000000000000000000000000 $
b00000000000000000000000000000000 %
b00000000000000000000000000000000 &
0'
b00000 (
0)
1*
b00000000000000000000000000000000 +
b00000000000000000000000000000001 ,
b00000000000000000000000000000010 -
b00000000000000000000000000000011 .
b00000000000000000000000000000100 /
b00000000000000000000000000000101 0
b00000000000000000000000000000110 1
b00000000000000000000000000000111 2
b00000000000000000000000000001000 3
b00000000000000000000000000001001 4
b00000000000000000000000000001010 5
b00000000000000000000000000001011 6
b00000000000000000000000000001100 7
b00000000000000000000000000001101 8
b00000000000000000000000000001110 9
b00000000000000000000000000001111 :
b00000000000000000000000000010000 ;
b00000000000000000000000000010001 <
b00000000000000000000000000010010 =
b00000000000000000000000000010011 >
b00000000000000000000000000010100 ?
b00000000000000000000000000010101 @
b00000000000000000000000000010110 A
b00000000000000000000000000010111 B
b00000000000000000000000000011000 C
b00000000000000000000000000011001 D
b00000000000000000000000000011010 E
b00000000000000000000000000011011 F
b00000000000000000000000000011100 G
b00000000000000000000000000011101 H
b00000000000000000000000000011110 I
b00000000000000000000000000011111 J
b00000000000000000000000000000000 K
0L
b00000000000000000000000000100000 M
b00000000000000000000000000100000 N
b00000000000000000000000000001010 O
#5
1L
#10
0*
0L
#15
1L
#20
b100 "
0L
#25
1L
#30
b000 "
1'
0L
#35
1L
#40
b100 "
1)
0L
#45
1L
#50
b010 "
b00000000000000000000000000000110 %
0)
b00000000000000000000000000000110 K
0L
#55
1L
#60
b001 "
b00000000000000000000000001000011 &
b00000000000000000000000000000000 K
0L
#65
b00000000000000000000000001000011 1
1L
#70
b010 "
b00000000000000000000000001000011 K
0L
